{
    "name": "Sorte",
    "icon": "minecraft:textures/mob_effect/luck.png",
    "category": "apotheosis:potion/recipes",
	"flag": "apotheosis:potion",
	"sortnum": 0,
    "pages": [
        {
            "type": "patchouli:text",
            "text": "$(6)Sorte$() é um efeito muito peculiar.$(p)Ter mais sorte significa que você pode receber um saque melhor de certas fontes.$(p)Infelizmente, não há como saber quais fontes de saque são afetadas por $(6)sorte$()."
        },
		{
            "type": "patchouli:spotlight",
			"title": "Receita de fabricação de poção",
			"item": "apotheosis:lucky_foot",
			"link_recipe": true,
            "text": "Esta poção pode ser criada com uma poção estranha e um pé de coelho da sorte.$(p)O Pé de coelho da sorte raramente é derrubado por coelhos."
        }
	]
}