{
    "name": "Resistência da armadura",
    "icon": "minecraft:netherite_chestplate",
    "category": "apotheosis:adventure/attributes",
	"flag": "apotheosis:adventure",
	"sortnum": 0,
    "pages": [
        {
            "type": "patchouli:text",
            "text": "$(9)Resistência da armadura$() é uma status que reduz a eficácia da redução de armadura recebida.$(p)Geralmente fornecido por itens de armaduras ou escudos."
        },
		{
			"type": "patchouli:text",
			"text": "Cada ponto de resistência da armadura reduz a eficácia de perfuração de armadura e fragmentação de armadura em 2%, até 60%.$(p)Esta função é exclusiva do Apotheosis. No Minecraft vanilla, resistência da armadura contribui para a redução de dano."
		}
	]
}